optopus/__init__.py
optopus/_draft.py
optopus/_draft_new.py
optopus/_old.py
optopus/bargparse.py
optopus/constants.py
optopus/errors.py
optopus/grammar.py
optopus/parser.py
optopus/version.py
optopus-0.3.0.dist-info/LICENSE
optopus-0.3.0.dist-info/METADATA
optopus-0.3.0.dist-info/WHEEL
optopus-0.3.0.dist-info/top_level.txt
optopus-0.3.0.dist-info/RECORD
