Metadata-Version: 2.1
Name: optopus
Version: 0.3.0
Summary: Command line arguments done right
Home-page: https://github.com/hindman/optopus
Author: Monty Hindman
Author-email: mhindman@gmail.com
License: MIT
Classifier: Development Status :: 3 - Alpha
Classifier: Environment :: Console
Classifier: Intended Audience :: Developers
Classifier: License :: OSI Approved :: MIT License
Classifier: Operating System :: OS Independent
Classifier: Programming Language :: Python :: 3.5
Classifier: Programming Language :: Python :: 3.6
Classifier: Programming Language :: Python :: 3.7
Classifier: Programming Language :: Python :: 3.8
Classifier: Programming Language :: Python :: 3.9
Classifier: Programming Language :: Python :: 3.10
Classifier: Topic :: Software Development
License-File: LICENSE
Requires-Dist: attrs
Requires-Dist: short-con
Provides-Extra: test
Requires-Dist: pytest-cov; extra == "test"
Requires-Dist: tox; extra == "test"
Provides-Extra: dev
Requires-Dist: invoke; extra == "dev"
Requires-Dist: ipython; extra == "dev"
Requires-Dist: pycodestyle; extra == "dev"
Requires-Dist: twine; extra == "dev"
Requires-Dist: virtualenv; extra == "dev"
Requires-Dist: virtualenvwrapper; extra == "dev"
